cl_fifo_and_alu_defines.vh
// Amazon FPGA Hardware Development Kit
//
// Copyright 2016 Amazon.com, Inc. or its affiliates. All Rights Reserved.
//
// Licensed under the Amazon Software License (the "License"). You may not use
// this file except in compliance with the License. A copy of the License is
// located at
//
//    http://aws.amazon.com/asl/
//
// or in the "license" file accompanying this file. This file is distributed on
// an "AS IS" BASIS, WITHOUT WARRANTIES OR CONDITIONS OF ANY KIND, express or
// implied. See the License for the specific language governing permissions and
// limitations under the License.

`ifndef CL_fifo_and_alu_DEFINES
`define CL_fifo_and_alu_DEFINES

// Put module name of the CL design here.  This is used to instantiate in top.sv
`define CL_NAME cl_fifo_and_alu

// Highly recommeneded.  For lib FIFO block, uses less async reset (take advantage of
// FPGA flop init capability).  This will help with routing resources.
`define FPGA_LESS_RST

// Register addresses used by the CL.
// Note, registers are byte addressable, and data is 4 bytes, so each 
// address is a multiple of 4
`define ALU_ONE_ADDR              32'h0000_0510
`define ALU_TWO_ADDR              32'h0000_0514

// Uncomment to disable Virtual JTAG
`define DISABLE_VJTAG_DEBUG

`endif

alu.v
/*
 * Copyright (C) 2018
 * Author: Adam Wolnikowski <adam.wolnikowski@yale.edu>
 *
 * This program is free software; you can redistribute it and/or modify
 * it under the terms of the GNU General Public License as published by
 * the Free Software Foundation; either version 3 of the License, or
 * (at your option) any later version.
 *
 * This program is distributed in the hope that it will be useful,
 * but WITHOUT ANY WARRANTY; without even the implied warranty of
 * MERCHANTABILITY or FITNESS FOR A PARTICULAR PURPOSE.  See the
 * GNU General Public License for more details.
 *
 * You should have received a copy of the GNU General Public License
 * along with this program; if not, write to the Free Software Foundation,
 * Inc., 51 Franklin Street, Fifth Floor, Boston, MA 02110-1301  USA
 *
*/

module alu(
    input wire clock,
    input wire reset_n,

    input wire                  empty,
    output reg                  rd,
    input [DATA_WIDTH-1:0]      din,

    input wire                  full,
    output reg                  wr,
    output reg [DATA_WIDTH-1:0] dout
);

// Parameters

parameter DATA_WIDTH = 32;

// ALU logic

localparam START = 0,
           SEND_READ = 1,
           GET_READ = 2,
           SAVE_OPCODE = 3,
           SAVE_ARG1 = 4,
           SAVE_ARG2 = 5,
           SAVE_ARG3 = 6,
           COMPUTE = 7,
           WRITE_RESULT = 8,
           NUM_STATES = 9;

//reg [$clog2(NUM_STATES)-1:0] state;
reg [3:0] state;
reg [3:0] ret_state;
reg [3:0] prev_state;

localparam OP_ADD = 0,
	   OP_MUL = 1,
     OP_MUL_ADD = 2,
	   NUM_OPCODES = 3;

reg [2:0] opcode;
reg [DATA_WIDTH-1:0] arg1;
reg [DATA_WIDTH-1:0] arg2;
reg [DATA_WIDTH-1:0] arg3;
reg [DATA_WIDTH-1:0] result;

always @(posedge clock) begin
  if (!reset_n) begin
    // reset all registers when the system starts
    state <= START;
    ret_state <= START;
    rd <= 0;
    wr <= 0;
    dout <= 0;
    opcode <= 0;
    arg1 <= 0;
    arg2 <= 0;
    arg3 <= 0;
    result <= 0;
  end
  else begin
    // default assignment of register values
    // if not affected by the case statement
    state <= state;
    ret_state <= ret_state;
    prev_state <= state;
    rd <= 0;
    wr <= 0;
    dout <= 0;
    opcode <= opcode;
    arg1 <= arg1;
    arg2 <= arg2;
    arg3 <= arg3;
    result <= result;

    // main state machine
    // how can you simplify it? =)
    case (state)

      START: begin
        state <= SEND_READ;
        ret_state <= SAVE_OPCODE;
      end

      SEND_READ: begin
        if (!empty) begin
          rd <= 1;
          state <= GET_READ;
        end
        else begin
          rd <= 0;
          state <= SEND_READ;
        end
      end

      GET_READ: begin
          state <= ret_state;
      end

      SAVE_OPCODE: begin
        opcode <= din;
        state <= SEND_READ;
        ret_state <= SAVE_ARG1;
      end

      SAVE_ARG1: begin
        arg1 <= din;
        state <= SEND_READ;
        ret_state <= SAVE_ARG2;
      end

      SAVE_ARG2: begin
        arg2 <= din;
        state <= SEND_READ;
        ret_state <= SAVE_ARG3;
      end

      SAVE_ARG3: begin
        arg3 <= din;
        state <= COMPUTE;
      end

      COMPUTE: begin
        case (opcode)
          OP_ADD: begin
            result <= arg1 + arg2;
          end

          OP_MUL: begin
            result <= arg1 * arg2;
          end

          OP_MUL_ADD: begin
            result <= (arg1 * arg2) + arg3;
          end

          // default : $display("Error in opcode case statement.");
        endcase
	state <= WRITE_RESULT;
      end

      WRITE_RESULT: begin
        if (!full) begin
	        wr <= 1;
          dout <= result;
          state <= START;
        end
        else begin
          dout <= 0;
          state <= WRITE_RESULT;
        end
      end

      //default: begin
      //  $display("Error in alu state machine case statement");
      //  $display("Got state %d, ret_state %d, prev_state %d", state, ret_state, prev_state);
      //end
    endcase

  end

end

endmodule

fifo.v
// Adapted by Adam Wolnikowski from:
// https://stackoverflow.com/questions/24027523/first-in-first-out-fifo-using-verilog

module fifo (
  input clock,
  input reset,

  input wr_in,
  input rd_in,
  input [DATA_WIDTH-1:0] din,
  output reg [DATA_WIDTH-1:0] dout,
  output empty,
  output full,

  output reg [DATA_WIDTH-1:0] fifo_cnt
);

// Parameters

parameter DATA_WIDTH = 32;
parameter ADDR_WIDTH = 4;
parameter RAM_DEPTH = (1 << ADDR_WIDTH);

// FIFO logic

reg [DATA_WIDTH-1:0] fifo_ram[0:RAM_DEPTH-1];
reg [ADDR_WIDTH-1:0] rd_ptr, wr_ptr;

assign empty = (fifo_cnt==0);
assign full = (fifo_cnt==8);

reg wr;
reg rd;
reg wr_in_d;
reg rd_in_d;

// edge detection
always @( posedge clock )
begin: edge_detect
  rd_in_d <= rd_in;
  wr_in_d <= wr_in;

  rd = (rd_in && !rd_in_d);
  wr = (wr_in && !wr_in_d);
end

always @( posedge clock )
begin: write
if(wr && !full) fifo_ram[wr_ptr] <= din;
else if(wr && rd) fifo_ram[wr_ptr] <= din;
end

always @( posedge clock )
begin: read
if(rd && !empty)
  dout <= fifo_ram[rd_ptr];
else if(rd && wr && empty)
  dout <= fifo_ram[rd_ptr];
end

always @( posedge clock )
begin: pointer
  if( reset )
  begin
    wr_ptr <= 0;
    rd_ptr <= 0;
  end
  else
  begin
    wr_ptr <= ((wr && !full)||(wr && rd)) ? wr_ptr+1 : wr_ptr;
    rd_ptr <= ((rd && !empty)||(wr && rd)) ? rd_ptr+1 : rd_ptr;
  end
end

always @( posedge clock )
begin: count
  if( reset )
    fifo_cnt <= 0;
  else
  begin
    case ({wr,rd})
      2'b00 : fifo_cnt <= fifo_cnt;
      2'b01 : fifo_cnt <= (fifo_cnt==0) ? 0 : fifo_cnt-1;
      2'b10 : fifo_cnt <= (fifo_cnt==8) ? 8 : fifo_cnt+1;
      2'b11 : fifo_cnt <= fifo_cnt;
      default: fifo_cnt <= fifo_cnt;
    endcase
  end
end


endmodule

axi4lite_to_fifos.v
/*
 * Copyright (C) 2018
 * Revised by Adam Wolnikowski
 *
 * This program is free software; you can redistribute it and/or modify
 * it under the terms of the GNU General Public License as published by
 * the Free Software Foundation; either version 3 of the License, or
 * (at your option) any later version.
 *
 * This program is distributed in the hope that it will be useful,
 * but WITHOUT ANY WARRANTY; without even the implied warranty of
 * MERCHANTABILITY or FITNESS FOR A PARTICULAR PURPOSE.  See the
 * GNU General Public License for more details.
 *
 * You should have received a copy of the GNU General Public License
 * along with this program; if not, write to the Free Software Foundation,
 * Inc., 51 Franklin Street, Fifth Floor, Boston, MA 02110-1301  USA
*/

`include "cl_fifo_and_alu_defines.vh" // to get define for ALU_ONE_ADDR

module axi4lite_to_fifos (
    input wire clk_main_a0,
    input wire rst_main_n_sync,

    // inputs to AXI-Lite slave
    input wire        awvalid,
    input wire [DATA_WIDTH-1:0] awaddr,
    input wire        wvalid,
    input wire [DATA_WIDTH-1:0] wdata,
    input wire [3:0]  wstrb,
    input wire        bready,
    input wire        arvalid,
    input wire [DATA_WIDTH-1:0] araddr,
    input wire        rready,

    // outputs from AXI-Lite slave
    output wire       awready,
    output wire       wready,
    output reg        bvalid,
    output wire [1:0] bresp,
    output wire       arready, // unexpectedly becomes one in the middle of read
    output reg        rvalid,
    output reg [DATA_WIDTH-1:0] rdata,
    output reg [1:0]  rresp,

    // connections to CL-to-ALU FIFO
    // (only writing to this FIFO, ALU does the reading)
    output reg fifo_cl_to_alu_wr,
    output reg [DATA_WIDTH-1:0] fifo_cl_to_alu_din,
    input wire fifo_cl_to_alu_full,

    // connections to ALU-to-CL FIFO
    // (only reading form this FIFO, ALU does the writing)
    output reg fifo_alu_to_cl_rd,
    input wire [DATA_WIDTH-1:0] fifo_alu_to_cl_dout,
    input wire fifo_alu_to_cl_empty
);

parameter DATA_WIDTH = 32;

// CL is a slave device, only responds to write and read requests from master
// cannot generate its own requestes.

// Write Request
reg        wr_active;
reg [31:0] wr_addr;

always @(posedge clk_main_a0)
  if (!rst_main_n_sync) begin
    wr_active <= 0;
    wr_addr   <= 0;
  end
  else begin
    wr_active <=  wr_active && bvalid  && bready ? 1'b0     :
                  ~wr_active && awvalid          ? 1'b1     :
                                                 wr_active  ;
    wr_addr <= awvalid && ~wr_active ? awaddr : wr_addr     ;
  end

assign awready = ~wr_active;
assign wready  =  wr_active && wvalid && !fifo_cl_to_alu_full;

// Write Response
always @(posedge clk_main_a0)
  if (!rst_main_n_sync)
    bvalid <= 0;
  else
    bvalid <=  bvalid &&  bready ? 1'b0  :
              ~bvalid &&  wready ? 1'b1  :
                                   bvalid;
assign bresp = 0;

// Read Request
reg        arvalid_q;
reg [31:0] araddr_q;

always @(posedge clk_main_a0)
  if (!rst_main_n_sync) begin
    arvalid_q <= 0;
    araddr_q  <= 0;
  end
  else begin
    arvalid_q <= arvalid;
    araddr_q  <= arvalid ? araddr : araddr_q;
  end

assign arready = !arvalid_q && !rvalid && !fifo_alu_to_cl_empty;


// Write to FIFO logic
always @(posedge clk_main_a0) begin

  if (!rst_main_n_sync) begin
    fifo_cl_to_alu_wr <= 0;
    fifo_cl_to_alu_din <= 0;
  end
  else if (wready & (wr_addr == `ALU_ONE_ADDR) & !fifo_cl_to_alu_full) begin
    fifo_cl_to_alu_wr <= 1;
    fifo_cl_to_alu_din <= wdata;
  end
  else begin
    fifo_cl_to_alu_wr <= 0;
    fifo_cl_to_alu_din <= 0;
  end
end

// Read from FIFO logic
localparam WAIT       = 0,
           IDLE       = 1,
           READ_FIFO  = 2,
           NUM_STATES = 3;

reg [1:0] state;

always @(posedge clk_main_a0) begin

  if (!rst_main_n_sync) begin
    rvalid <= 0;
    rdata  <= 0;
    rresp  <= 0;
    fifo_alu_to_cl_rd <= 0;
    state <= IDLE;  // Initial state is IDLE
  end
  else begin
    case(state)
      WAIT: begin
        rvalid <= 0;
        rdata  <= 0;
        rresp  <= 0;
        fifo_alu_to_cl_rd <= 0;
        state <= READ_FIFO;
      end

      IDLE: begin
        if (rvalid && rready) begin
          rvalid <= 0;
          rdata  <= 0;
          rresp  <= 0;
          fifo_alu_to_cl_rd <= 0;
          state <= IDLE;
        end
        else if (arvalid_q && (araddr_q == `ALU_ONE_ADDR) && !fifo_alu_to_cl_empty) begin
          rvalid <= 0;
          rdata  <= 0;
          rresp  <= 0;
          fifo_alu_to_cl_rd <= 1;
          state <= WAIT; //fifo requires 2 cycles to get data
        end
      end

      READ_FIFO: begin
        rvalid <= 1;
        rdata <= fifo_alu_to_cl_dout;
        rresp  <= 0;
        fifo_alu_to_cl_rd <= 0;
        state <= IDLE;
      end

    endcase
  end
end

endmodule

axi_fifo_alu_tb/axi_fifo_alu_tb.v
/*
 * Copyright (C) 2018
 * Author: Adam Wolnikowski <adam.wolnikowski@yale.edu>
 *
 * This program is free software; you can redistribute it and/or modify
 * it under the terms of the GNU General Public License as published by
 * the Free Software Foundation; either version 3 of the License, or
 * (at your option) any later version.
 *
 * This program is distributed in the hope that it will be useful,
 * but WITHOUT ANY WARRANTY; without even the implied warranty of
 * MERCHANTABILITY or FITNESS FOR A PARTICULAR PURPOSE.  See the
 * GNU General Public License for more details.
 *
 * You should have received a copy of the GNU General Public License
 * along with this program; if not, write to the Free Software Foundation,
 * Inc., 51 Franklin Street, Fifth Floor, Boston, MA 02110-1301  USA
 *
*/

`include "cl_fifo_and_alu_defines.vh"
`timescale 1ns / 1ps

module axi_fifo_alu_tb;

localparam DATA_WIDTH = 32;

// AXI Inputs
reg clk = 1'b0;
reg rst = 1'b1; // reset is active low, so 1 means not resetting

reg awvalid = 1'b0;
reg [DATA_WIDTH-1:0] awaddr = 32'h0000_0000;
reg wvalid = 1'b0;
reg [DATA_WIDTH-1:0] wdata = 32'h0000_0000;
reg [3:0] wstrb = 4'b0000;
reg bready = 1'b0;
reg arvalid = 1'b0;
reg [DATA_WIDTH-1:0] araddr = 32'h0000_0000;
reg rready = 1'b0;

// AXI Outputs
wire awready;
wire wready;
wire bvalid;
wire [1:0] bresp;
wire arready;
wire rvalid;
wire [DATA_WIDTH-1:0] rdata;
wire [1:0] rresp;

// axi/fifo connections
wire fin_wr;
wire [DATA_WIDTH-1:0] fin_din;
wire fin_full;

wire fout_rd;
wire [DATA_WIDTH-1:0] fout_dout;
wire fout_empty;

axi4lite_to_fifos axi (
    .clk_main_a0(clk),
    .rst_main_n_sync(rst),
    .awvalid(awvalid),
    .awaddr(awaddr),
    .wvalid(wvalid),
    .wdata(wdata),
    .wstrb(wstrb),
    .bready(bready),
    .arvalid(arvalid),
    .araddr(araddr),
    .rready(rready),
    .awready(awready),
    .wready(wready),
    .bvalid(bvalid),
    .bresp(bresp),
    .arready(arready),
    .rvalid(rvalid),
    .rdata(rdata),
    .rresp(rresp),
    .fifo_cl_to_alu_wr(fin_wr),
    .fifo_cl_to_alu_din(fin_din),
    .fifo_cl_to_alu_full(fin_full),
    .fifo_alu_to_cl_rd(fout_rd),
    .fifo_alu_to_cl_dout(fout_dout),
    .fifo_alu_to_cl_empty(fout_empty)
  );

//alu/fifo connections
wire fin_rd;
wire [DATA_WIDTH-1:0] fin_dout;
wire fin_empty;

wire fout_wr;
wire [DATA_WIDTH-1:0] fout_din;
wire fout_full;

wire [DATA_WIDTH-1:0] fin_cnt;
wire [DATA_WIDTH-1:0] fout_cnt;

fifo fifo_in (
    .clock(clk),
    .reset(~rst),
    .wr_in(fin_wr), // from axi
    .rd_in(fin_rd), // from alu
    .din(fin_din), // from axi
    .dout(fin_dout), // to alu
    .empty(fin_empty), // to alu
    .full(fin_full), // to axi
    .fifo_cnt(fin_cnt)
  );

fifo fifo_out (
    .clock(clk),
    .reset(~rst),
    .wr_in(fout_wr), // from alu
    .rd_in(fout_rd), // from axi
    .din(fout_din), // from alu
    .dout(fout_dout), // to axi
    .empty(fout_empty), // to axi
    .full(fout_full), // to alu
    .fifo_cnt(fout_cnt)
  );

alu alu (
    .clock(clk),
    .reset_n(rst),
    .empty(fin_empty),
    .rd(fin_rd),
    .din(fin_dout),
    .full(fout_full),
    .wr(fout_wr),
    .dout(fout_din)
  );

// write out signals to waveform
initial
  begin
    $dumpfile("axi_fifo_alu_tb.vcd");
    $dumpvars(0, axi_fifo_alu_tb);
  end

// main simulation process
initial
  begin
    # 25;
    rst <= 0;
    # 25;
    rst <= 1;
    # 25
    $display("\nWriting Opcode: 1 (Mul)",);
    awaddr <= `ALU_ONE_ADDR;
    awvalid <= 1;
    wdata <= 32'h0000_0001;
    wvalid <= 1;
    wstrb <= 4'b0001;
    bready <= 1;
    @(negedge bvalid);
    $display("\nWriting Arg1: 2",);
    awaddr <= `ALU_ONE_ADDR;
    awvalid <= 1;
    wdata <= 32'h0000_0002;
    wvalid <= 1;
    wstrb <= 4'b0001;
    bready <= 1;
    @(negedge bvalid);
    $display("\nWriting Arg2: 3",);
    awaddr <= `ALU_ONE_ADDR;
    awvalid <= 1;
    wdata <= 32'h0000_0003;
    wvalid <= 1;
    wstrb <= 4'b0001;
    bready <= 1;
    @(negedge bvalid);
    $display("\nWriting Arg3: 0",);
    awaddr <= `ALU_ONE_ADDR;
    awvalid <= 1;
    wdata <= 32'h0000_0000;
    wvalid <= 1;
    wstrb <= 4'b0001;
    bready <= 1;
    @(negedge bvalid);
    $display("\nWriting Opcode: 2 (Mul-Add)",);
    awaddr <= `ALU_ONE_ADDR;
    awvalid <= 1;
    wdata <= 32'h0000_0002;
    wvalid <= 1;
    wstrb <= 4'b0001;
    bready <= 1;
    @(negedge bvalid);
    $display("\nWriting Arg1: 2",);
    awaddr <= `ALU_ONE_ADDR;
    awvalid <= 1;
    wdata <= 32'h0000_0002;
    wvalid <= 1;
    wstrb <= 4'b0001;
    bready <= 1;
    @(negedge bvalid);
    $display("\nWriting Arg2: 3",);
    awaddr <= `ALU_ONE_ADDR;
    awvalid <= 1;
    wdata <= 32'h0000_0003;
    wvalid <= 1;
    wstrb <= 4'b0001;
    bready <= 1;
    @(negedge bvalid);
    $display("\nWriting Arg3: 4",);
    awaddr <= `ALU_ONE_ADDR;
    awvalid <= 1;
    wdata <= 32'h0000_0004;
    wvalid <= 1;
    wstrb <= 4'b0001;
    bready <= 1;
    @(negedge bvalid);
    awaddr <= 32'h0000_0000;
    awvalid <= 0;
    wdata <= 32'h0000_0000;
    wvalid <= 0;
    wstrb <= 4'b0000;
    bready <= 0;

    # 25
    araddr <= `ALU_ONE_ADDR;
    arvalid <= 1;
    rready <= 1;
    @(posedge rvalid);
    $display("\nReading result 1: %0d", rdata);
    @(negedge rvalid);
    araddr <= `ALU_ONE_ADDR;
    arvalid <= 1;
    rready <= 1;
    @(posedge rvalid);
    $display("\nReading result 2: %0d", rdata);
    @(negedge rvalid);
    araddr <= 32'h0000_0000;
    arvalid <= 0;
    rready <= 0;

    $fflush();
    # 25;
    $display("\nSIMULATION FINISHED\n");
    $fflush();
    $finish;
  end

// toggle the clock
always
  # 5 clk = !clk;

endmodule

axi_fifo_alu_tb/axi_fifo_alu_tb.vcd
$date
	Mon Nov  5 12:10:38 2018
$end
$version
	Icarus Verilog
$end
$timescale
	1ps
$end
$scope module axi_fifo_alu_tb $end
$var wire 1 ! arready $end
$var wire 1 " awready $end
$var wire 2 # bresp [1:0] $end
$var wire 1 $ bvalid $end
$var wire 32 % fin_cnt [31:0] $end
$var wire 32 & fin_din [31:0] $end
$var wire 32 ' fin_dout [31:0] $end
$var wire 1 ( fin_empty $end
$var wire 1 ) fin_full $end
$var wire 1 * fin_rd $end
$var wire 1 + fin_wr $end
$var wire 32 , fout_cnt [31:0] $end
$var wire 32 - fout_din [31:0] $end
$var wire 32 . fout_dout [31:0] $end
$var wire 1 / fout_empty $end
$var wire 1 0 fout_full $end
$var wire 1 1 fout_rd $end
$var wire 1 2 fout_wr $end
$var wire 32 3 rdata [31:0] $end
$var wire 2 4 rresp [1:0] $end
$var wire 1 5 rvalid $end
$var wire 1 6 wready $end
$var reg 32 7 araddr [31:0] $end
$var reg 1 8 arvalid $end
$var reg 32 9 awaddr [31:0] $end
$var reg 1 : awvalid $end
$var reg 1 ; bready $end
$var reg 1 < clk $end
$var reg 1 = rready $end
$var reg 1 > rst $end
$var reg 32 ? wdata [31:0] $end
$var reg 4 @ wstrb [3:0] $end
$var reg 1 A wvalid $end
$scope module axi $end
$var wire 32 B araddr [31:0] $end
$var wire 1 ! arready $end
$var wire 1 C arvalid $end
$var wire 32 D awaddr [31:0] $end
$var wire 1 " awready $end
$var wire 1 E awvalid $end
$var wire 1 F bready $end
$var wire 2 G bresp [1:0] $end
$var wire 1 H clk_main_a0 $end
$var wire 32 I fifo_alu_to_cl_dout [31:0] $end
$var wire 1 / fifo_alu_to_cl_empty $end
$var wire 1 ) fifo_cl_to_alu_full $end
$var wire 1 J rready $end
$var wire 1 K rst_main_n_sync $end
$var wire 32 L wdata [31:0] $end
$var wire 1 6 wready $end
$var wire 4 M wstrb [3:0] $end
$var wire 1 N wvalid $end
$var reg 32 O araddr_q [31:0] $end
$var reg 1 P arvalid_q $end
$var reg 1 Q bvalid $end
$var reg 1 R fifo_alu_to_cl_rd $end
$var reg 32 S fifo_cl_to_alu_din [31:0] $end
$var reg 1 T fifo_cl_to_alu_wr $end
$var reg 32 U rdata [31:0] $end
$var reg 2 V rresp [1:0] $end
$var reg 1 W rvalid $end
$var reg 2 X state [1:0] $end
$var reg 1 Y wr_active $end
$var reg 32 Z wr_addr [31:0] $end
$upscope $end
$scope module fifo_in $end
$var wire 1 H clock $end
$var wire 32 [ din [31:0] $end
$var wire 1 ( empty $end
$var wire 1 ) full $end
$var wire 1 * rd_in $end
$var wire 1 \ reset $end
$var wire 1 + wr_in $end
$var reg 32 ] dout [31:0] $end
$var reg 32 ^ fifo_cnt [31:0] $end
$var reg 1 _ rd $end
$var reg 1 ` rd_in_d $end
$var reg 4 a rd_ptr [3:0] $end
$var reg 1 b wr $end
$var reg 1 c wr_in_d $end
$var reg 4 d wr_ptr [3:0] $end
$scope begin edge_detect $end
$upscope $end
$scope begin write $end
$upscope $end
$scope begin read $end
$upscope $end
$scope begin pointer $end
$upscope $end
$scope begin count $end
$upscope $end
$upscope $end
$scope module fifo_out $end
$var wire 1 H clock $end
$var wire 32 e din [31:0] $end
$var wire 1 / empty $end
$var wire 1 0 full $end
$var wire 1 1 rd_in $end
$var wire 1 f reset $end
$var wire 1 2 wr_in $end
$var reg 32 g dout [31:0] $end
$var reg 32 h fifo_cnt [31:0] $end
$var reg 1 i rd $end
$var reg 1 j rd_in_d $end
$var reg 4 k rd_ptr [3:0] $end
$var reg 1 l wr $end
$var reg 1 m wr_in_d $end
$var reg 4 n wr_ptr [3:0] $end
$scope begin edge_detect $end
$upscope $end
$scope begin write $end
$upscope $end
$scope begin read $end
$upscope $end
$scope begin pointer $end
$upscope $end
$scope begin count $end
$upscope $end
$upscope $end
$scope module alu $end
$var wire 1 H clock $end
$var wire 32 o din [31:0] $end
$var wire 1 ( empty $end
$var wire 1 0 full $end
$var wire 1 K reset_n $end
$var reg 32 p arg1 [31:0] $end
$var reg 32 q arg2 [31:0] $end
$var reg 32 r arg3 [31:0] $end
$var reg 32 s dout [31:0] $end
$var reg 3 t opcode [2:0] $end
$var reg 4 u prev_state [3:0] $end
$var reg 1 v rd $end
$var reg 32 w result [31:0] $end
$var reg 4 x ret_state [3:0] $end
$var reg 4 y state [3:0] $end
$var reg 1 z wr $end
$upscope $end
$upscope $end
$enddefinitions $end
#0
$dumpvars
xz
bx y
bx x
bx w
xv
bx u
bx t
bx s
bx r
bx q
bx p
bx o
bx n
xm
xl
bx k
xj
xi
bx h
bx g
0f
bx e
bx d
xc
xb
bx a
x`
x_
bx ^
bx ]
0\
bx [
bx Z
xY
bx X
xW
bx V
bx U
xT
bx S
xR
xQ
xP
bx O
0N
b0 M
b0 L
1K
0J
bx I
0H
b0 G
0F
0E
b0 D
0C
b0 B
0A
b0 @
b0 ?
1>
0=
0<
0;
0:
b0 9
08
b0 7
06
x5
bx 4
bx 3
x2
x1
x0
x/
bx .
bx -
bx ,
x+
x*
x)
x(
bx '
bx &
bx %
x$
b0 #
x"
x!
$end
#5000
0P
b0 S
b0 &
b0 [
0T
0+
b0 s
b0 -
b0 e
0z
02
0v
0*
1<
1H
#10000
0<
0H
#15000
0m
0c
0`
0l
0b
0_
1<
1H
#20000
0<
0H
#25000
1f
1\
0>
0K
1<
1H
#30000
0<
0H
#35000
0!
1"
b0 h
1/
00
b0 ,
b0 k
b0 n
b0 ^
1(
0)
b0 %
b0 a
b0 d
b0 w
b0 r
b0 q
b0 p
b0 t
b0 x
b0 y
b1 X
0R
01
b0 V
b0 4
b0 U
b0 3
0W
05
b0 O
0Q
0$
b0 Z
0Y
1<
1H
#40000
0<
0H
#45000
0j
0i
1<
1H
#50000
0f
0\
1>
1K
0<
0H
#55000
b11 x
b1 y
b0 u
1<
1H
#60000
0<
0H
#65000
b1 u
1<
1H
#70000
0<
0H
#75000
1;
1F
b1 @
b1 M
1A
1N
b1 ?
b1 L
1:
1E
b10100010000 9
b10100010000 D
1<
1H
#80000
0<
0H
#85000
16
0"
b10100010000 Z
1Y
1<
1H
#90000
0<
0H
#95000
b1 S
b1 &
b1 [
1T
1+
1Q
1$
1<
1H
#100000
0<
0H
#105000
b10 ?
b10 L
06
1"
b1 ^
0(
b1 %
b1 d
1c
0Y
0Q
0$
1b
1<
1H
#110000
0<
0H
#115000
16
0"
b10 y
1v
1*
b0 S
b0 &
b0 [
0T
0+
1Y
0b
1<
1H
#120000
0<
0H
#125000
b0 ^
1(
b0 %
b1 a
b1 ]
b1 '
b1 o
0c
1`
1Q
1$
b10 S
b10 &
b10 [
1T
1+
b11 y
0v
0*
b10 u
1_
1<
1H
#130000
0<
0H
#135000
b11 ?
b11 L
06
1"
b1 ^
0(
b1 %
b10 d
1c
0`
b100 x
b1 y
b1 t
b11 u
0Q
0$
0Y
1b
0_
1<
1H
#140000
0<
0H
#145000
16
0"
1Y
b0 S
b0 &
b0 [
0T
0+
b10 y
1v
1*
b1 u
0b
1<
1H
#150000
0<
0H
#155000
b0 ^
1(
b0 %
b10 a
b10 ]
b10 '
b10 o
0c
1`
b100 y
0v
0*
b10 u
b11 S
b11 &
b11 [
1T
1+
1Q
1$
1_
1<
1H
#160000
0<
0H
#165000
b0 ?
b0 L
06
1"
b1 ^
0(
b1 %
b11 d
1c
0`
0Y
0Q
0$
b101 x
b1 y
b10 p
b100 u
1b
0_
1<
1H
#170000
0<
0H
#175000
16
0"
b10 y
1v
1*
b1 u
b0 S
b0 &
b0 [
0T
0+
1Y
0b
1<
1H
#180000
0<
0H
#185000
b0 ^
1(
b0 %
b11 a
b11 ]
b11 '
b11 o
0c
1`
1Q
1$
1T
1+
b101 y
0v
0*
b10 u
1_
1<
1H
#190000
0<
0H
#195000
b10 ?
b10 L
06
1"
b1 ^
0(
b1 %
b100 d
1c
0`
b110 x
b1 y
b11 q
b101 u
0Q
0$
0Y
1b
0_
1<
1H
#200000
0<
0H
#205000
16
0"
1Y
0T
0+
b10 y
1v
1*
b1 u
0b
1<
1H
#210000
0<
0H
#215000
b0 ^
1(
b0 %
b100 a
b0 ]
b0 '
b0 o
0c
1`
b110 y
0v
0*
b10 u
b10 S
b10 &
b10 [
1T
1+
1Q
1$
1_
1<
1H
#220000
0<
0H
#225000
06
1"
b1 ^
0(
b1 %
b101 d
1c
0`
0Y
0Q
0$
b111 y
b110 u
1b
0_
1<
1H
#230000
0<
0H
#235000
16
0"
b1000 y
b110 w
b111 u
b0 S
b0 &
b0 [
0T
0+
1Y
0b
1<
1H
#240000
0<
0H
#245000
0c
1Q
1$
b10 S
b10 &
b10 [
1T
1+
b0 y
b110 s
b110 -
b110 e
1z
12
b1000 u
1<
1H
#250000
0<
0H
#255000
b11 ?
b11 L
06
1!
1"
b1 h
0/
b1 ,
b1 n
1m
b10 ^
b10 %
b110 d
1c
b11 x
b1 y
b0 s
b0 -
b0 e
0z
02
b0 u
0Q
0$
0Y
1l
1b
1<
1H
#260000
0<
0H
#265000
16
0"
0m
1Y
b0 S
b0 &
b0 [
0T
0+
b10 y
1v
1*
b1 u
0l
0b
1<
1H
#270000
0<
0H
#275000
b1 ^
b1 %
b101 a
b10 ]
b10 '
b10 o
0c
1`
b11 y
0v
0*
b10 u
b11 S
b11 &
b11 [
1T
1+
1Q
1$
1_
1<
1H
#280000
0<
0H
#285000
b100 ?
b100 L
06
1"
b10 ^
b10 %
b111 d
1c
0`
0Y
0Q
0$
b100 x
b1 y
b10 t
b11 u
1b
0_
1<
1H
#290000
0<
0H
#295000
16
0"
b10 y
1v
1*
b1 u
b0 S
b0 &
b0 [
0T
0+
1Y
0b
1<
1H
#300000
0<
0H
#305000
b1 ^
b1 %
b110 a
0c
1`
1Q
1$
b100 S
b100 &
b100 [
1T
1+
b100 y
0v
0*
b10 u
1_
1<
1H
#310000
0<
0H
#315000
0;
0F
b0 @
b0 M
0A
0N
b0 ?
b0 L
0:
0E
b0 9
b0 D
06
1"
b10 ^
b10 %
b1000 d
1c
0`
b101 x
b1 y
b100 u
0Q
0$
0Y
1b
0_
1<
1H
#320000
0<
0H
#325000
b0 S
b0 &
b0 [
0T
0+
b10 y
1v
1*
b1 u
0b
1<
1H
#330000
0<
0H
#335000
b1 ^
b1 %
b111 a
b11 ]
b11 '
b11 o
0c
1`
b101 y
0v
0*
b10 u
1_
1<
1H
#340000
1=
1J
18
1C
b10100010000 7
b10100010000 B
0<
0H
#345000
0!
0`
b10100010000 O
1P
b110 x
b1 y
b101 u
0_
1<
1H
#350000
0<
0H
#355000
b10 y
1v
1*
b1 u
b0 X
1R
11
1<
1H
#360000
0<
0H
#365000
b0 h
1/
b0 ,
b1 k
b110 g
b110 .
b110 I
1j
b0 ^
1(
b0 %
b1000 a
b100 ]
b100 '
b100 o
1`
b10 X
0R
01
b110 y
0v
0*
b10 u
1i
1_
1<
1H
#370000
0<
0H
#375000
0j
0`
b111 y
b100 r
b110 u
b1 X
b110 U
b110 3
1W
15
0i
0_
1<
1H
#380000
0<
0H
#385000
b0 U
b0 3
0W
05
b1000 y
b1010 w
b111 u
1<
1H
#390000
0<
0H
#395000
b0 y
b1010 s
b1010 -
b1010 e
1z
12
b1000 u
1<
1H
#400000
0<
0H
#405000
b1 h
0/
b1 ,
b10 n
1m
b11 x
b1 y
b0 s
b0 -
b0 e
0z
02
b0 u
1l
1<
1H
#410000
0<
0H
#415000
0m
b1 u
b0 X
1R
11
0l
1<
1H
#420000
0<
0H
#425000
b0 h
1/
b0 ,
b10 k
b1010 g
b1010 .
b1010 I
1j
b10 X
0R
01
1i
1<
1H
#430000
0<
0H
#435000
0j
b1 X
b1010 U
b1010 3
1W
15
0i
1<
1H
#440000
0<
0H
#445000
0=
0J
08
0C
b0 7
b0 B
b0 U
b0 3
0W
05
1<
1H
#450000
0<
0H
#455000
0P
1<
1H
